setup.py
LoreleiLib/Character.py
LoreleiLib/CombatHelpers.py
LoreleiLib/Helpers.py
LoreleiLib/Map.py
LoreleiLib/Objects.py
LoreleiLib/Statistics.py
LoreleiLib/StringHelpers.py
LoreleiLib/__init__.py
LoreleiLib.egg-info/PKG-INFO
LoreleiLib.egg-info/SOURCES.txt
LoreleiLib.egg-info/dependency_links.txt
LoreleiLib.egg-info/not-zip-safe
LoreleiLib.egg-info/requires.txt
LoreleiLib.egg-info/top_level.txt
LoreleiLib/Packets/CharacterCreation.py
LoreleiLib/Packets/Common.py
LoreleiLib/Packets/Login.py
LoreleiLib/Packets/View.py
LoreleiLib/Packets/__init__.py
LoreleiLib/Packets/Game/Chat.py
LoreleiLib/Packets/Game/Room.py
LoreleiLib/Packets/Game/__init__.py