Metadata-Version: 1.0
Name: LoreleiLib
Version: 0.1.7.5
Summary: The text based MUD made by Lorinthio
Home-page: UNKNOWN
Author: Lorinthio
Author-email: benrandallswg@gmail.com
License: UNKNOWN
Platform: UNKNOWN
